Metadata-Version: 2.1
Name: exercise-package
Version: 1.0.0
Summary: This is package for exercise!
Author: ysy
Author-email: ysy@qq.com
License-File: LICENSE.txt
